{
  "title": "Technical Evaluation - IT Department",
  "department": "it",
  "duration": "120",
  "instructions": "Please answer the following questions to the best of your ability. This evaluation is designed to assess your technical knowledge, problem-solving ability, creativity, communication skills, and practical IT experience. IMPORTANT: For practical development, website, and graphic design tasks, upload your work publicly on Google Drive, GitHub, Behance, Figma, Canva, Netlify, Vercel, or any accessible platform. Then create a text (.txt) file containing the links to your uploaded work clearly labeled according to the respective question numbers. Email the text file as an attachment to misc@tradesmartzm.com before submission.",
  "sections": [
    {
      "title": "ENGLISH LANGUAGE & COMMUNICATION",
      "points": 15,
      "questions": [
        {
          "id": 1,
          "title": "Grammar",
          "content": "The IT Officer ________ responsible for maintaining the company network.",
          "points": 3,
          "inputs": [
            {
              "type": "radio",
              "options": ["is", "are", "were"]
            }
          ]
        },
        {
          "id": 2,
          "title": "Vocabulary",
          "content": "A firewall helps to ________ unauthorized access to a network.",
          "points": 3,
          "inputs": [
            {
              "type": "radio",
              "options": ["prevent", "promote", "replace"]
            }
          ]
        },
        {
          "id": 3,
          "title": "Professional Communication",
          "content": "Write a short email responding to a staff member whose laptop cannot connect to the office Wi-Fi.",
          "points": 4,
          "inputs": [
            {
              "type": "paragraph"
            }
          ]
        },
        {
          "id": 4,
          "title": "Customer Support",
          "content": "How would you explain a technical issue to a non-technical staff member?",
          "points": 5,
          "inputs": [
            {
              "type": "paragraph"
            }
          ]
        }
      ]
    },
    {
      "title": "COMPUTER HARDWARE & TROUBLESHOOTING",
      "points": 20,
      "questions": [
        {
          "id": 5,
          "title": "Troubleshooting",
          "content": "A user reports that their computer powers on but displays a black screen. Explain the troubleshooting steps you would take.",
          "points": 5,
          "inputs": [
            {
              "type": "paragraph"
            }
          ]
        },
        {
          "id": 6,
          "title": "Networking",
          "content": "A laptop connects to Wi-Fi but has no internet access. What could be the possible causes and solutions?",
          "points": 5,
          "inputs": [
            {
              "type": "paragraph"
            }
          ]
        },
        {
          "id": 7,
          "title": "Hardware Knowledge",
          "content": "Name and explain the function of any four major computer hardware components.",
          "points": 5,
          "inputs": [
            {
              "type": "paragraph"
            }
          ]
        },
        {
          "id": 8,
          "title": "Preventative Maintenance",
          "content": "What regular maintenance activities should be carried out on office computers and servers?",
          "points": 5,
          "inputs": [
            {
              "type": "paragraph"
            }
          ]
        }
      ]
    },
    {
      "title": "NETWORKING & SYSTEM ADMINISTRATION",
      "points": 20,
      "questions": [
        {
          "id": 9,
          "title": "IP Addressing",
          "content": "What is an IP address and why is it important in networking?",
          "points": 5,
          "inputs": [
            {
              "type": "paragraph"
            }
          ]
        },
        {
          "id": 10,
          "title": "Active Directory & User Management",
          "content": "Explain the process of creating and managing user accounts in an organization.",
          "points": 5,
          "inputs": [
            {
              "type": "paragraph"
            }
          ]
        },
        {
          "id": 11,
          "title": "Data Backup",
          "content": "Describe a good backup and disaster recovery strategy for a company.",
          "points": 5,
          "inputs": [
            {
              "type": "paragraph"
            }
          ]
        },
        {
          "id": 12,
          "title": "Server Monitoring",
          "content": "What tools or methods can be used to monitor server performance, backups, and security?",
          "points": 5,
          "inputs": [
            {
              "type": "paragraph"
            }
          ]
        }
      ]
    },
    {
      "title": "CYBER SECURITY",
      "points": 15,
      "questions": [
        {
          "id": 13,
          "title": "Security Awareness",
          "content": "What are phishing attacks and how can employees avoid them?",
          "points": 5,
          "inputs": [
            {
              "type": "paragraph"
            }
          ]
        },
        {
          "id": 14,
          "title": "Password Security",
          "content": "What makes a strong password policy in an organization?",
          "points": 5,
          "inputs": [
            {
              "type": "paragraph"
            }
          ]
        },
        {
          "id": 15,
          "title": "Endpoint Protection",
          "content": "List and explain three ways to secure company computers and data.",
          "points": 5,
          "inputs": [
            {
              "type": "paragraph"
            }
          ]
        }
      ]
    },
    {
      "title": "WEBSITE MANAGEMENT & SOFTWARE DEVELOPMENT",
      "points": 20,
      "questions": [
        {
          "id": 16,
          "title": "Website Management",
          "content": "Describe the steps you would take to update and maintain a company website.",
          "points": 5,
          "inputs": [
            {
              "type": "paragraph"
            }
          ]
        },
        {
          "id": 17,
          "title": "Software Development",
          "content": "What programming languages, frameworks, or technologies are you familiar with? Explain how you have used them.",
          "points": 5,
          "inputs": [
            {
              "type": "paragraph"
            }
          ]
        },
        {
          "id": 18,
          "title": "Practical Development Task",
          "content": "Create a simple responsive webpage for Tradesmart Supplies Limited that includes a homepage banner, company description, and contact section. Upload the project publicly (GitHub, Google Drive, Netlify, Vercel, etc.). Include the public link in the text file and email it to misc@tradesmartzm.com.",
          "points": 10,
          "inputs": [
            {
              "type": "null"
            }
          ]
        }
      ]
    },
    {
      "title": "GRAPHIC DESIGN & DIGITAL MEDIA",
      "points": 20,
      "questions": [
        {
          "id": 19,
          "title": "Graphic Design Knowledge",
          "content": "Which graphic design tools have you used before and for what type of projects?",
          "points": 5,
          "inputs": [
            {
              "type": "paragraph"
            }
          ]
        },
        {
          "id": 20,
          "title": "Poster Design Task",
          "content": "Design a professional promotional poster for Tradesmart Supplies Limited advertising an IT service or product. Upload the design publicly (Google Drive, Behance, Canva, Figma, etc.). Include the public link in the text file and email it to misc@tradesmartzm.com.",
          "points": 10,
          "inputs": [
            {
              "type": "null"
            }
          ]
        },
        {
          "id": 21,
          "title": "Social Media Creativity",
          "content": "Create a sample social media post design for Tradesmart Supplies Limited promoting cybersecurity awareness. Upload the design publicly and include the accessible link in the text file emailed to misc@tradesmartzm.com.",
          "points": 5,
          "inputs": [
            {
              "type": "null"
            }
          ]
        }
      ]
    },
    {
      "title": "PRACTICAL SCENARIOS & PROBLEM SOLVING",
      "points": 25,
      "questions": [
        {
          "id": 22,
          "title": "Office IT Support",
          "content": "An employee accidentally deleted important company files. Explain the steps you would take to recover the files.",
          "points": 5,
          "inputs": [
            {
              "type": "paragraph"
            }
          ]
        },
        {
          "id": 23,
          "title": "Network Downtime",
          "content": "The office internet suddenly stops working during business hours. Describe your troubleshooting process.",
          "points": 5,
          "inputs": [
            {
              "type": "paragraph"
            }
          ]
        },
        {
          "id": 24,
          "title": "System Upgrade",
          "content": "How would you plan and execute a company-wide operating system upgrade with minimal downtime?",
          "points": 5,
          "inputs": [
            {
              "type": "paragraph"
            }
          ]
        },
        {
          "id": 25,
          "title": "IT Policy",
          "content": "What IT policies would you recommend for employees regarding email usage, passwords, and internet access?",
          "points": 5,
          "inputs": [
            {
              "type": "paragraph"
            }
          ]
        },
        {
          "id": 26,
          "title": "Innovation & Improvement",
          "content": "Suggest three ways technology can improve efficiency and productivity at Tradesmart Supplies Limited.",
          "points": 5,
          "inputs": [
            {
              "type": "paragraph"
            }
          ]
        }
      ]
    }
  ]
}